CamAge_package/__init__.py
CamAge_package/segmentation.py
CamAge_package/mrcnn/__init__.py
CamAge_package/mrcnn/config.py
CamAge_package/mrcnn/convert_to_image.py
CamAge_package/mrcnn/model.py
CamAge_package/mrcnn/my_bowl_dataset.py
CamAge_package/mrcnn/my_functions.py
CamAge_package/mrcnn/my_inference.py
CamAge_package/mrcnn/my_inference_tta.py
CamAge_package/mrcnn/my_train_1.py
CamAge_package/mrcnn/my_train_2.py
CamAge_package/mrcnn/my_train_3.py
CamAge_package/mrcnn/parallel_model.py
CamAge_package/mrcnn/preprocess_images.py
CamAge_package/mrcnn/utils.py
CamAge_package/mrcnn/visualize.py
CamAgeTest2-0.0.1.dist-info/METADATA
CamAgeTest2-0.0.1.dist-info/WHEEL
CamAgeTest2-0.0.1.dist-info/top_level.txt
CamAgeTest2-0.0.1.dist-info/RECORD
